setup.py
pilpe/__init__.py
pilpe/pipeline.py
pilpe.egg-info/PKG-INFO
pilpe.egg-info/SOURCES.txt
pilpe.egg-info/dependency_links.txt
pilpe.egg-info/top_level.txt
pilpe/plugins/__init__.py
pilpe/plugins/ocr.py
pilpe/plugins/pdf.py
pilpe/plugins/plugin.py
test/__init__.py
test/ocr_pdf.py
test/data/__init__.py