Metadata-Version: 1.0
Name: pilpe
Version: 0.1
Summary: A image pipeline to apply filters in one or more images.
Home-page: UNKNOWN
Author: Sergio Campos
Author-email: seocam@seocam.net
License: UNKNOWN
Platform: UNKNOWN
